CHANGES.rst
MANIFEST.in
README.rst
setup.cfg
setup.py
docs/LICENSE.txt
docs/TODO.txt
mtj/__init__.py
mtj.jibber.egg-info/PKG-INFO
mtj.jibber.egg-info/SOURCES.txt
mtj.jibber.egg-info/dependency_links.txt
mtj.jibber.egg-info/entry_points.txt
mtj.jibber.egg-info/namespace_packages.txt
mtj.jibber.egg-info/not-zip-safe
mtj.jibber.egg-info/requires.txt
mtj.jibber.egg-info/top_level.txt
mtj/jibber/__init__.py
mtj/jibber/bot.py
mtj/jibber/core.py
mtj/jibber/ctrl.py
mtj/jibber/jabber.py
mtj/jibber/presence.py
mtj/jibber/stanza.py
mtj/jibber/utils.py
mtj/jibber/configs/muc_bot.client.config.json.example
mtj/jibber/configs/muc_bot_extended.client.config.json.example
mtj/jibber/configs/server.config.json.example
mtj/jibber/testing/__init__.py
mtj/jibber/testing/client.py
mtj/jibber/testing/command.py