Metadata-Version: 1.1
Name: mtj.jibber
Version: 0.4
Summary: A very easy to use, simple to extend jabber bot framework.
Home-page: https://github.com/metatoaster/mtj.jibber/
Author: Tommy Yu
Author-email: y@metatoaster.com
License: mit
Platform: UNKNOWN
Classifier: Development Status :: 4 - Beta
Classifier: Environment :: Console
Classifier: Intended Audience :: Developers
Classifier: License :: OSI Approved :: MIT License
Classifier: Programming Language :: Python
Classifier: Programming Language :: Python :: 2.7
Classifier: Programming Language :: Python :: 3.3
Classifier: Programming Language :: Python :: 3.4
Classifier: Programming Language :: Python :: Implementation :: PyPy
Classifier: Topic :: Internet
Classifier: Topic :: Utilities
